split_screen_mcp/__init__.py
split_screen_mcp/__main__.py
split_screen_mcp/functions.py
split_screen_macos_test_copy-0.2.0.dist-info/METADATA
split_screen_macos_test_copy-0.2.0.dist-info/WHEEL
split_screen_macos_test_copy-0.2.0.dist-info/entry_points.txt
split_screen_macos_test_copy-0.2.0.dist-info/licenses/LICENSE
split_screen_macos_test_copy-0.2.0.dist-info/RECORD
