Metadata-Version: 2.4
Name: split-screen-macOS-test-copy
Version: 0.2.0
Summary: Model Context Protocol Server for macOS Window Management and Split-Screen Operations
Author: Beta
Maintainer: Beta
License: MIT License
License-File: LICENSE
Keywords: accessibility,macos,mcp,model-context-protocol,split-screen,window-management
Classifier: Development Status :: 4 - Beta
Classifier: Intended Audience :: Developers
Classifier: License :: OSI Approved :: MIT License
Classifier: Operating System :: MacOS
Classifier: Programming Language :: Python :: 3
Classifier: Programming Language :: Python :: 3.9
Classifier: Programming Language :: Python :: 3.10
Classifier: Programming Language :: Python :: 3.11
Classifier: Programming Language :: Python :: 3.12
Classifier: Topic :: Desktop Environment :: Window Managers
Classifier: Topic :: Software Development :: Libraries :: Python Modules
Classifier: Topic :: System :: Systems Administration
Requires-Python: >=3.9
Requires-Dist: mcp>=0.1.0
Requires-Dist: pyobjc-core<11,>=10.1
Requires-Dist: pyobjc-framework-applicationservices<11,>=10.1
Requires-Dist: pyobjc-framework-cocoa<11,>=10.1
Requires-Dist: pyobjc-framework-quartz<11,>=10.1
